LibMTL/__init__.py
LibMTL/_record.py
LibMTL/config.py
LibMTL/loss.py
LibMTL/metrics.py
LibMTL/trainer.py
LibMTL/utils.py
LibMTL/architecture/CGC.py
LibMTL/architecture/Cross_stitch.py
LibMTL/architecture/DSelect_k.py
LibMTL/architecture/HPS.py
LibMTL/architecture/MMoE.py
LibMTL/architecture/MTAN.py
LibMTL/architecture/PLE.py
LibMTL/architecture/__init__.py
LibMTL/architecture/abstract_arch.py
LibMTL/model/__init__.py
LibMTL/model/resnet.py
LibMTL/model/resnet_dilated.py
LibMTL/weighting/CAGrad.py
LibMTL/weighting/DWA.py
LibMTL/weighting/EW.py
LibMTL/weighting/GLS.py
LibMTL/weighting/GradDrop.py
LibMTL/weighting/GradNorm.py
LibMTL/weighting/GradVac.py
LibMTL/weighting/IMTL.py
LibMTL/weighting/MGDA.py
LibMTL/weighting/PCGrad.py
LibMTL/weighting/RLW.py
LibMTL/weighting/UW.py
LibMTL/weighting/__init__.py
LibMTL/weighting/abstract_weighting.py
LibMTL-1.1.5.dist-info/LICENSE
LibMTL-1.1.5.dist-info/METADATA
LibMTL-1.1.5.dist-info/WHEEL
LibMTL-1.1.5.dist-info/top_level.txt
LibMTL-1.1.5.dist-info/RECORD
