Metadata-Version: 2.1
Name: LibMTL
Version: 1.1.5
Summary: A PyTorch Library for Multi-Task Learning
Home-page: https://github.com/median-research-group/LibMTL
Author: Baijiong Lin
Author-email: linbj@mail.sustech.edu.cn
License: MIT
Platform: all
Classifier: Intended Audience :: Developers
Classifier: Intended Audience :: Education
Classifier: Intended Audience :: Science/Research
Classifier: License :: OSI Approved :: MIT License
Classifier: Programming Language :: Python :: 3.7
Classifier: Programming Language :: Python :: 3.8
Classifier: Programming Language :: Python :: 3.9
Classifier: Programming Language :: Python :: 3.10
Classifier: Topic :: Scientific/Engineering :: Artificial Intelligence
Classifier: Topic :: Scientific/Engineering :: Mathematics
Classifier: Topic :: Software Development :: Libraries
License-File: LICENSE
Requires-Dist: torch (>=1.8.0)
Requires-Dist: torchvision (>=0.9.0)
Requires-Dist: numpy (>=1.20)
